{"schema_version":1,"generated_at":"2026-04-25T17:38:35.353063Z","source":"NYC DOHMH (NYC EH Data Portal; aggregated from SPARCS, since raw SPARCS rows are not publicly released)","indicator":"Asthma emergency department visit rate, ages 0-17, by ZCTA","period":"2022 (most recent published 12-month window)","nyc_avg_per_10k":92.4,"zctas":{"10454":{"name":"Mott Haven","borough":"Bronx","rate_per_10k_children":412.7,"visits":187,"ratio_to_nyc_avg":4.47,"one_in_n":24},"10474":{"name":"Hunts Point","borough":"Bronx","rate_per_10k_children":395.3,"visits":117,"ratio_to_nyc_avg":4.28,"one_in_n":25},"10458":{"name":"Fordham","borough":"Bronx","rate_per_10k_children":278.4,"visits":498,"ratio_to_nyc_avg":3.01,"one_in_n":36},"10463":{"name":"Kingsbridge","borough":"Bronx","rate_per_10k_children":142.1,"visits":171,"ratio_to_nyc_avg":1.54,"one_in_n":70},"10024":{"name":"Upper West Side","borough":"Manhattan","rate_per_10k_children":58.6,"visits":67,"ratio_to_nyc_avg":0.63,"one_in_n":171},"10001":{"name":"Midtown","borough":"Manhattan","rate_per_10k_children":72.4,"visits":25,"ratio_to_nyc_avg":0.78,"one_in_n":138},"10009":{"name":"East Village","borough":"Manhattan","rate_per_10k_children":94.8,"visits":59,"ratio_to_nyc_avg":1.03,"one_in_n":105},"11216":{"name":"Bed-Stuy","borough":"Brooklyn","rate_per_10k_children":308.5,"visits":425,"ratio_to_nyc_avg":3.34,"one_in_n":32},"11226":{"name":"Flatbush","borough":"Brooklyn","rate_per_10k_children":204.2,"visits":456,"ratio_to_nyc_avg":2.21,"one_in_n":49},"11373":{"name":"Elmhurst","borough":"Queens","rate_per_10k_children":88.1,"visits":164,"ratio_to_nyc_avg":0.95,"one_in_n":114},"11432":{"name":"Jamaica","borough":"Queens","rate_per_10k_children":154.6,"visits":230,"ratio_to_nyc_avg":1.67,"one_in_n":65},"10301":{"name":"St. George","borough":"Staten Island","rate_per_10k_children":95.3,"visits":60,"ratio_to_nyc_avg":1.03,"one_in_n":105}}}